LICENSE
MANIFEST.in
README.md
requirements.txt
setup.cfg
setup.py
django_mp_shop_products.egg-info/PKG-INFO
django_mp_shop_products.egg-info/SOURCES.txt
django_mp_shop_products.egg-info/dependency_links.txt
django_mp_shop_products.egg-info/top_level.txt
products/__init__.py
products/constants.py
products/utils.py
products/forms/__init__.py
products/forms/product_image.py
products/locale/en/LC_MESSAGES/django.mo
products/locale/en/LC_MESSAGES/django.po
products/locale/ru/LC_MESSAGES/django.mo
products/locale/ru/LC_MESSAGES/django.po
products/locale/uk/LC_MESSAGES/django.mo
products/locale/uk/LC_MESSAGES/django.po
products/models/__init__.py
products/models/product.py
products/models/product_category.py
products/models/product_flag.py
products/models/product_image.py