Metadata-Version: 1.1
Name: django-mp-shop-products
Version: 1.0
Summary: Django shop products apps
Home-page: https://github.com/pmaigutyak/mp-shop-products
Author: Paul Maigutyak
Author-email: pmaigutyak@gmail.com
License: MIT
Download-URL: https://github.com/pmaigutyak/mp-shop-products/archive/1.0.tar.gz
Platform: UNKNOWN
